core/__init__.py
core/latex_generator.py
core/llm_client.py
core/pdf_processor.py
examples/basic.py
examples/other_basic.py
pysearchlm-1.0.1.dist-info/licenses/LICENSE
utils/__init__.py
utils/config.py
utils/helpers.py
pysearchlm-1.0.1.dist-info/METADATA
pysearchlm-1.0.1.dist-info/WHEEL
pysearchlm-1.0.1.dist-info/top_level.txt
pysearchlm-1.0.1.dist-info/RECORD
