Metadata-Version: 2.4
Name: pysearchlm
Version: 1.0.1
Summary: LLM-powered PDF academic paper summarizer with LaTeX output
Author-email: Semih Ocakli <semihocakli35@gmail.com>
License: MIT
Project-URL: Homepage, https://github.com/Semihocakli/pysearchlm
Project-URL: Repository, https://github.com/Semihocakli/pysearchlm
Project-URL: Issues, https://github.com/Semihocakli/pysearchlm/issues
Classifier: Programming Language :: Python :: 3
Classifier: Programming Language :: Python :: 3.8
Classifier: Programming Language :: Python :: 3.9
Classifier: Programming Language :: Python :: 3.10
Classifier: Programming Language :: Python :: 3.11
Classifier: Programming Language :: Python :: 3.12
Classifier: Intended Audience :: Developers
Classifier: Intended Audience :: Science/Research
Classifier: Topic :: Scientific/Engineering :: Artificial Intelligence
Classifier: Topic :: Text Processing :: Markup :: LaTeX
Classifier: Operating System :: OS Independent
Requires-Python: >=3.8
License-File: LICENSE
Requires-Dist: google-generativeai>=0.8.3
Requires-Dist: requests>=2.32.3
Requires-Dist: python-dotenv>=1.0.1
Dynamic: license-file
